django_datetime_helpers/__init__.py
django_datetime_helpers/helpers.py
django_datetime_helpers-0.0.1.dist-info/LICENSE
django_datetime_helpers-0.0.1.dist-info/METADATA
django_datetime_helpers-0.0.1.dist-info/WHEEL
django_datetime_helpers-0.0.1.dist-info/top_level.txt
django_datetime_helpers-0.0.1.dist-info/RECORD
